ndautomata/VERSION
ndautomata/__init__.py
ndautomata/initializers.py
ndautomata/neighbours.py
ndautomata-1.0.5.dist-info/LICENSE
ndautomata-1.0.5.dist-info/METADATA
ndautomata-1.0.5.dist-info/WHEEL
ndautomata-1.0.5.dist-info/top_level.txt
ndautomata-1.0.5.dist-info/RECORD
