Metadata-Version: 2.1
Name: ndautomata
Version: 1.0.5
Summary: Multidimensional cellular automata in Python.
License: GNU General Public License v3 (GPLv3)
Project-URL: Homepage, https://github.com/BorjaEst/ndautomata/
Project-URL: Bug Tracker, https://github.com/BorjaEst/ndautomata/issues
Classifier: Programming Language :: Python :: 3
Classifier: License :: OSI Approved :: GNU General Public License v3 (GPLv3)
Classifier: Operating System :: OS Independent
Requires-Python: >=3.10
License-File: LICENSE
Requires-Dist: pydantic (~=2.0.2)
Requires-Dist: numpy (~=1.25.1)
Requires-Dist: scipy (~=1.11.1)
Requires-Dist: matplotlib (~=3.7.2)
